{
  "id": "venge-io",
  "name": "Venge.io",
  "author": "Poki",
  "description": "Venge.io is an online multiplayer First-Person Shooter game. It is a fast-paced shooter with an engaged and competitive community. There are four standard game modes and maps and countless custom maps/game modes. Play with 7 different weapons and 4 different heroes. In the shop you can buy skins for your heroes and camos for your guns. Invite your friends by sharing the link in the lobby screen and enjoy this amazing game together! You can play Venge.io completely for free on your PC, mobile phone, or tablet. There is no download needed, just access the game directly in your browser. For the PC we also have full-screen mode available. Enjoy playing Venge.io on Poki and maybe we will see you on top of the leaderboards! Maps & Game Modes Sierra - POINT You play a game mode similar to capture-the-flag/domination in a desert-like map. The goal is staying in the green area (Flag Point) and unlock tier abilities. The capture time varies around 1 minute. Xibalba - BLACKCOIN You play a game mode where you have to collect 'Black Coins' after killing someone in a dark mysterious map. The goal is to collect these coins after killing someone, and thereafter 'deliver' them to the green area in the temple. Tundra - GUNGAME You play the classic game mode gun-game in a winter-like map. The goal is to play through all different weapons. After every kill your rank up and get to play a different weapon. Mistle - PAYLOAD You play a refreshing new game mode in a small town-like map. The goal of this game mode is to push a minecart to the opponent's side. You do this by standing in the green area around the cart. Within this green area, you can unlock your abilities. Scraper - POINT A Strategic map inspired by Asian culture for close or medium range battles. Stay in the green area and protect it from other players to get score. Upgrade character abilities and use your tactical skills to win! Loadout Heroes You can play as 4 different heroes; Lilium, Shin, Echo, and Kulu. All the characte",
  "thumbnail": "/games/venge-io/online/assets/venge-io.png",
  "category": "io"
}
