{
  "id": "domino",
  "name": "Domino",
  "author": "Poki",
  "description": "Domino brings the timeless classic board game online! Choose to play with 2, 3, or 4 players and enjoy smooth, strategic matches anytime, anywhere. Face off against new opponents as you match tiles, block plays, and aim to be the first to go out. Ready to lay your tiles and dominate the table? How to play Domino? Click or tap to make the choice. Who created Domino? Domino is created by Kzunec Games. Play their other games on Poki: Polygon Master and Pixel Fishing How can I play Domino for free? You can play Domino for free on Poki. Can I play Domino on mobile devices and desktop? Domino can be played on your computer and mobile devices like phones and tablets.",
  "thumbnail": "/games/domino/online/assets/domino.png",
  "category": "brain"
}
