{
  "id": "words-emoji",
  "name": "Words Emoji",
  "author": "Poki",
  "description": "Words Emoji is a word puzzle game created by WeDoYouPlay. Combine letters into meaningful words in accordance with the help of the emojis you see on the bottom of the page. Level up by completing the puzzles and challenge yourself as the words get more difficult. The more words you can guess, the more coins you can earn. If you're stuck on a puzzle, use the hint button at the top of the page to reveal one of the words by spending the coins you've earned. Words Emoji is the perfect way to kill some time while improving your vocabulary. How to play: Click a letter to start a line, and drag over other letters to form meaningful words. Words Emoji is created by WeDoYouPlay. This is their first game on Poki!",
  "thumbnail": "/games/words-emoji/online/assets/words-emoji.png",
  "category": "puzzle"
}
