{
  "id": "funny-tattoo-shop",
  "name": "Funny Tattoo Shop",
  "author": "Poki",
  "description": "Are you looking for Tattoo games to play? Then you have come to the right parlor. Funny Tattoo Shop is the ultimate tattoo game, created by Go Panda games it mixes the dress up and simulation genres. You are the successful owner of a tattoo parlor, and you're responsible for giving a wide range of customers cool and colorful tattoos. Choose the right design for your customer depending on your perception of their personality. Draw the tattoo carefully, clean the skin, and then treat it with the right colors. You will love the look on your customers' faces when they are happy with your creations. Don't forget to share your artworks with your friends! How to play? Use your mouse cursor to select, drag and move objects around. Who created Funny Tattoo Shop? Funny Tattoo Shop is created by Go Panda Games. They have similar funny games like funny-rescue-gardener, Funny Hair Salon , Funny Nose Surgery , funny-rescue-zookeeper and funny-pet-rescue. Their other games include Cooking Korean Lesson and Hipster vs Rockers . Play them all on Poki for free!",
  "thumbnail": "/games/funny-tattoo-shop/online/assets/funny-tattoo-shop.png",
  "category": "simulation"
}
