{
  "id": "popular-words",
  "name": "Popular Words",
  "author": "Poki",
  "description": "Popular Words is a word game where your vocabulary, knowledge, and intuition are put to the test! Explore a wide range of questions across various topics and discover the top five most common answers. With each level presenting a fill-in-the-blank question, it's up to you to uncover the most popular responses. Keep an eye out for hints, as the first letters of the correct answers are provided to guide you along the way. Are you ready to find out the popular words that await you? How to play Popular Words? Use the keyboard or mouse to type in your answers. Who created Popular Words? Popular Words is created by Unico Studio. Play their other games on Poki: Brain Test: Tricky Puzzles , Brain Test 2: Tricky Stories , Brain Test 3: Tricky Quests , Brain Test 4: Tricky Friends , Brain Test: Tricky Words , Who Is? , Who is? 2 Brain Puzzle & Chats , Life Choices: Life Simulator , Word City Crossed , Word City Uncrossed , 4 Pics 1 Word and Word Monsters ! How can I play Popular Words for free? You can play Popular Words for free on Poki. Can I play Popular Words on mobile devices and desktop? Popular Words can be played on your computer and mobile devices like phones and tablets.",
  "thumbnail": "/games/popular-words/online/assets/popular-words.png",
  "category": "words"
}
