{
  "id": "papas-wingeria",
  "name": "Papa's Wingeria",
  "author": "Poki",
  "description": "In this new entry in the Papa's series, you're off to Starlight City! Here, you'll play as either Chuck or Mandi and take on the role of the head chef for Papa Louie's newest venture: a chicken wings restaurant! It's up to you to take the orders, fry the chicken, apply the right sauces and arrange beautiful platters. Happy customers will increase your score and tip you more money, which you can spend on decorating your restaurant. Can you make the best wings and build the greatest restaurant Starlight City has ever seen? How to play Papa's Wingeria? Use the to navigate your way trough the kitchen and make the best wings! Who created Papa's Wingeria Papa's Wingeria is created by Flipline Studios. Play their other games on Poki: Papa's Burgeria , Papa's Freezeria , Papa's Pizzeria and Jacksmith How can I play Papa's Wingeria for free? You can play Papa's Wingeria for free on Poki. Can I play Papa's Wingeria on mobile devices and desktop? Papa's Wingeria can be played on your computer and mobile devices like phones and tablets.",
  "thumbnail": "/games/papas-wingeria/online/assets/papas-wingeria.png",
  "category": "flash"
}
